<?xml version="1.0" encoding="utf-8"?>
<publishData>
  <publishProfile publishUrl="C:\umkc\AgileMind\AgileMindSoap" deleteExistingFiles="False" ftpAnonymousLogin="False" ftpPassiveMode="True" msdeploySite="" msdeploySiteID="" msdeployRemoteSitePhysicalPath="" msdeployAllowUntrustedCertificate="False" msdeploySkipExtraFilesOnServer="True" msdeployMarkAsApp="False" profileName="Profile1" publishMethod="FileSystem" replaceMatchingFiles="True" userName="" savePWD="False" userPWD="" SelectedForPublish="True">
    <file relUrl="bin/AgileMind.DAL.dll" publishTime="03/07/2013 20:27:17" />
    <file relUrl="bin/AgileMind.BLL.dll" publishTime="03/09/2013 20:35:59" />
    <file relUrl="bin/AgileMind.BLL.pdb" publishTime="03/09/2013 20:35:59" />
    <file relUrl="bin/AgileMind.DAL.pdb" publishTime="03/07/2013 20:27:17" />
    <file relUrl="bin/AgileMind.SOAP.pdb" publishTime="03/10/2013 14:49:05" />
    <file relUrl="Web.config" publishTime="03/10/2013 14:50:59" />
    <file relUrl="Login.asmx" publishTime="03/10/2013 14:50:05" />
    <file relUrl="GamesService.asmx" publishTime="03/10/2013 14:50:15" />
    <file relUrl="Global.asax" publishTime="03/03/2013 20:27:17" />
    <file relUrl="bin/AgileMind.SOAP.dll" publishTime="03/10/2013 14:49:05" />
  </publishProfile>
</publishData>